quaxed/__init__.py
quaxed/_jax.py
quaxed/_setup.py
quaxed/_types.py
quaxed/_utils.py
quaxed/_version.py
quaxed/_version.pyi
quaxed/operator.py
quaxed/operator.pyi
quaxed/py.typed
quaxed/experimental/__init__.py
quaxed/lax/__init__.py
quaxed/lax/__init__.pyi
quaxed/lax/_patch.py
quaxed/lax/linalg.py
quaxed/lax/linalg.pyi
quaxed/numpy/__init__.py
quaxed/numpy/_core.py
quaxed/numpy/_creation_functions.py
quaxed/numpy/_higher_order.py
quaxed/numpy/fft.py
quaxed/numpy/linalg.py
quaxed/scipy/__init__.py
quaxed/scipy/linalg.py
quaxed/scipy/special.py
quaxed/scipy/special.pyi
quaxed/numpy/__init__.pyi
quaxed-0.10.4.dist-info/METADATA
quaxed-0.10.4.dist-info/WHEEL
quaxed-0.10.4.dist-info/licenses/LICENSE
quaxed-0.10.4.dist-info/RECORD
