Metadata-Version: 2.4
Name: quaxed
Version: 0.10.4
Summary: Pre-quaxed libraries for multiple dispatch over abstract array types in JAX
Project-URL: Homepage, https://github.com/GalacticDynamics/quaxed
Project-URL: Bug Tracker, https://github.com/GalacticDynamics/quaxed/issues
Project-URL: Discussions, https://github.com/GalacticDynamics/quaxed/discussions
Project-URL: Changelog, https://github.com/GalacticDynamics/quaxed/releases
Author-email: Nathaniel Starkman <nstarman@users.noreply.github.com>
License-File: LICENSE
Classifier: Development Status :: 1 - Planning
Classifier: Intended Audience :: Developers
Classifier: Intended Audience :: Science/Research
Classifier: License :: OSI Approved :: BSD License
Classifier: Operating System :: OS Independent
Classifier: Programming Language :: Python
Classifier: Programming Language :: Python :: 3
Classifier: Programming Language :: Python :: 3 :: Only
Classifier: Programming Language :: Python :: 3.11
Classifier: Programming Language :: Python :: 3.12
Classifier: Programming Language :: Python :: 3.13
Classifier: Topic :: Scientific/Engineering
Classifier: Typing :: Typed
Requires-Python: >=3.11
Requires-Dist: equinox>=0.13.2
Requires-Dist: jax>=0.5.3
Requires-Dist: jaxtyping>=0.3.1
Requires-Dist: optype>=0.8.0
Requires-Dist: plum-dispatch>=2.5.2
Requires-Dist: quax>=0.2.1
